{
  "printing": {
    "id": "contract-printer",
    "name": "Contract Printer",
    "model": "Contract 3000",
    "type": "FDM",
    "status": "printing",
    "online": true,
    "stateText": "printing",
    "stateMessage": null,
    "updatedAt": "2026-07-12T12:00:00.000Z",
    "job": "benchy.gcode",
    "progress": 42.5,
    "nozzle": [
      215,
      220
    ],
    "bed": [
      60,
      60
    ],
    "chamber": 31,
    "minutesLeft": 87,
    "material": "PETG",
    "swatch": "#4c4f55",
    "nozzleDiameter": 0.4,
    "nozzleDiameterSource": "printer",
    "nozzleType": "hardened_steel",
    "nozzleTypeSource": "printer",
    "liveMaterial": "PETG",
    "liveMaterialColor": "#112233",
    "liveMaterialSource": "printer",
    "activeTray": 1,
    "camera": "online",
    "cameraStream": true,
    "cameraSrc": "contract",
    "light": true,
    "lightSupported": false,
    "snapshotAt": "2026-07-12T12:00:00.000Z",
    "snapshotAvailable": true,
    "latestSnapshotUrl": "/api/printers/contract-printer/snapshots/snap-1",
    "filesSupported": true,
    "remoteStartSupported": true,
    "interfaceUrl": "http://printer.internal.example:4408"
  },
  "completed": {
    "id": "contract-printer",
    "name": "Contract Printer",
    "model": "Contract 3000",
    "type": "FDM",
    "status": "idle",
    "online": true,
    "stateText": "complete",
    "stateMessage": null,
    "updatedAt": "2026-07-12T12:00:00.000Z",
    "job": "benchy.gcode",
    "progress": 100,
    "nozzle": [
      215,
      220
    ],
    "bed": [
      60,
      60
    ],
    "chamber": 31,
    "minutesLeft": 0,
    "material": "PETG",
    "swatch": "#4c4f55",
    "nozzleDiameter": 0.4,
    "nozzleDiameterSource": "printer",
    "nozzleType": "hardened_steel",
    "nozzleTypeSource": "printer",
    "liveMaterial": "PETG",
    "liveMaterialColor": "#112233",
    "liveMaterialSource": "printer",
    "activeTray": 1,
    "camera": "online",
    "cameraStream": true,
    "cameraSrc": "contract",
    "light": true,
    "lightSupported": false,
    "snapshotAt": "2026-07-12T12:00:00.000Z",
    "snapshotAvailable": true,
    "latestSnapshotUrl": null,
    "filesSupported": true,
    "remoteStartSupported": true,
    "interfaceUrl": "http://printer.internal.example:4408"
  },
  "errored": {
    "id": "contract-printer",
    "name": "Contract Printer",
    "model": "Contract 3000",
    "type": "FDM",
    "status": "error",
    "online": true,
    "stateText": "error",
    "stateMessage": "Nozzle thermal runaway",
    "updatedAt": "2026-07-12T12:00:00.000Z",
    "job": "benchy.gcode",
    "progress": 42.5,
    "nozzle": [
      215,
      220
    ],
    "bed": [
      60,
      60
    ],
    "chamber": 31,
    "minutesLeft": 87,
    "material": "PETG",
    "swatch": "#4c4f55",
    "nozzleDiameter": 0.4,
    "nozzleDiameterSource": "printer",
    "nozzleType": "hardened_steel",
    "nozzleTypeSource": "printer",
    "liveMaterial": "PETG",
    "liveMaterialColor": "#112233",
    "liveMaterialSource": "printer",
    "activeTray": 1,
    "camera": "online",
    "cameraStream": true,
    "cameraSrc": "contract",
    "light": true,
    "lightSupported": false,
    "snapshotAt": "2026-07-12T12:00:00.000Z",
    "snapshotAvailable": true,
    "latestSnapshotUrl": null,
    "filesSupported": true,
    "remoteStartSupported": true,
    "interfaceUrl": "http://printer.internal.example:4408",
    "error": "Nozzle thermal runaway"
  },
  "offline": {
    "id": "contract-offline",
    "name": "Contract Offline",
    "model": "Contract 3000",
    "type": "FDM",
    "status": "unknown",
    "online": false,
    "stateText": null,
    "stateMessage": null,
    "updatedAt": null,
    "job": null,
    "progress": null,
    "nozzle": null,
    "bed": null,
    "chamber": null,
    "minutesLeft": null,
    "material": "PETG",
    "swatch": "#4c4f55",
    "nozzleDiameter": null,
    "nozzleDiameterSource": "unknown",
    "nozzleType": null,
    "nozzleTypeSource": "unknown",
    "liveMaterial": null,
    "liveMaterialColor": null,
    "liveMaterialSource": "config",
    "activeTray": null,
    "camera": "offline",
    "cameraStream": false,
    "cameraSrc": null,
    "light": null,
    "lightSupported": false,
    "snapshotAt": null,
    "snapshotAvailable": true,
    "latestSnapshotUrl": null,
    "filesSupported": true,
    "remoteStartSupported": true,
    "interfaceUrl": "http://printer.internal.example:4408"
  }
}
